Assignment_7/verilog/ESL_bus_demo/quad_decod.v
//
// Authors: D. Gaethofs, D.A. Rooijackers
// Title: Assignment 4 
// Brief: 
//

module quad_decod(
    input quadA, 
    input quadB, 
    input clk, 
    input reset,
    output wire [15:0] out, 
    output wire [1:0] direction_out
);

    reg [15:0] count = 0;
    reg [1:0] direction = 0;
    reg [1:0] curr_state = 2'b00;
    reg [1:0] prev_state = 2'b00;
    reg [1:0] sync = 2'b00;

always @ (posedge clk)
begin
    sync <= {quadA, quadB};
    curr_state <= sync;
end

always @ (posedge clk or posedge reset)
begin
    if (reset)
        begin
            count <= 0;
            direction <= 0;
            prev_state <= 2'b00;
        end
    
    case (curr_state)
        2'b00:
            begin
                if (prev_state == 2'b01)
                    begin
                        count <= count + 1;
                        prev_state <= curr_state;
                        direction <= 2'b01; //right
                    end 
                else if (prev_state == 2'b10)
                    begin
                       count <= count - 1;
                       prev_state <= curr_state;
                       direction <= 2'b10; //left 
                    end
            end
        2'b01:
            begin
                if (prev_state == 2'b00)
                    begin
                        count <= count - 1;
                        prev_state <= curr_state;
                        direction <= 2'b10; //left
                    end 
                else if (prev_state == 2'b11)
                    begin
                       count <= count + 1;
                       prev_state <= curr_state;
                       direction <= 2'b01; //right 
                    end
            end
        2'b10:
            begin
                if (prev_state == 2'b00)
                    begin
                        count <= count + 1;
                        prev_state <= curr_state;
                        direction <= 2'b10; //right
                    end 
                else if (prev_state == 2'b11)
                    begin
                       count <= count - 1;
                       prev_state <= curr_state;
                       direction <= 2'b01; //left 
                    end
            end
        2'b11:
            begin
                if (prev_state == 2'b10)
                    begin
                        count <= count + 1;
                        prev_state <= curr_state;
                        direction <= 2'b10; //right
                    end 
                else if (prev_state == 2'b01)
                    begin
                       count <= count - 1;
                       prev_state <= curr_state;
                       direction <= 2'b01; //left 
                    end
            end
    endcase

end

assign out = count;
assign direction_out = direction;

endmodule

Assignment_7/testbench/quad_decod_demo.v
module quad_decod_demo #(
        parameter DATA_WIDTH = 32
	) (
		input  wire [7:0]  slave_address,     //      avs_s0.address
		input  wire        slave_read,        //            .read
		output reg  [DATA_WIDTH-1:0] slave_readdata,    //            .readdata
		input  wire        slave_write,       //            .write
		input  wire [DATA_WIDTH-1:0] slave_writedata,   //            .writedata
		input  wire        clk,          //       clock.clk
        input  wire        reset,
        input  wire [(DATA_WIDTH/8)-1:0] slave_byteenable,
		output wire [7:0]  user_output,         // user_output.new_signal
        // output wire [1:0] user_output_2 // user_output_2.new_signal
        // input wire PITCH_ENC_A,
        // input wire PITCH_ENC_B
        input wire [3:0] SW
	);

    
    wire [15:0] count;
    wire [1:0] direction;

    // Definition of the counter
    quad_decod my_ip (
        .clk(clk),
        .reset(reset),
        // .quadA(PITCH_ENC_A),
        // .quadB(PITCH_ENC_B),
        .quadA(SW[0]),
        .quadB(SW[1]),
        .out(count),
        .direction_out(direction)
    );

    assign user_output = count[7:0];

    always @(posedge clk or posedge reset) begin
        if (reset) begin
            slave_readdata <= 32'b0;
        end else begin
            if (slave_read) begin
                slave_readdata <= {14'b0, direction, count};
            end
        end;
    end

endmodule

Assignment_7/testbench/quad_decod_demo_tb_advanced.v
`timescale 1ns / 1ps

module quad_decod_demo_tb_advanced;

    // Parameters
    parameter DATA_WIDTH = 32;
    parameter CLK_PERIOD = 20; // 50 MHz clock

    // Testbench Signals
    reg                     clk;
    reg                     reset;
    reg  [7:0]              slave_address;
    reg                     slave_read;
    wire [DATA_WIDTH-1:0]   slave_readdata;
    reg                     slave_write;
    reg  [DATA_WIDTH-1:0]   slave_writedata;
    reg  [(DATA_WIDTH/8)-1:0] slave_byteenable;
    wire [7:0]              user_output;
    reg  [3:0]              SW;

    // UUT (Unit Under Test) Instance
    quad_decod_demo #(
        .DATA_WIDTH(DATA_WIDTH)
    ) uut (
        .slave_address(slave_address),
        .slave_read(slave_read),
        .slave_readdata(slave_readdata),
        .slave_write(slave_write),
        .slave_writedata(slave_writedata),
        .clk(clk),
        .reset(reset),
        .slave_byteenable(slave_byteenable),
        .user_output(user_output),
        .SW(SW)
    );

    // Clock Generation
    always #(CLK_PERIOD/2) clk = ~clk;

    // -----------------------------------------------------------
    // TESTBENCH TASKS
    // -----------------------------------------------------------
    integer enc_state = 0; 
    
    // Task: Simulate physical rotation of the encoder
    // dir: 1 for CW (Right), 0 for CCW (Left)
    task rotate_encoder(input integer steps, input integer dir);
        integer i;
        begin
            for(i = 0; i < steps; i = i + 1) begin
                // Update internal gray code state tracker
                if (dir == 1) 
                    enc_state = (enc_state + 1) % 4;
                else 
                    enc_state = (enc_state - 1 + 4) % 4;

                // Map state tracker to Quadrature Gray Code (A, B)
                case(enc_state)
                    0: SW = 4'b0000; // 00
                    1: SW = 4'b0001; // 01
                    2: SW = 4'b0011; // 11
                    3: SW = 4'b0010; // 10
                endcase
                
                // Wait for the synchronous logic to process the edge
                #(CLK_PERIOD * 5); 
            end
        end
    endtask

    // Task: Perform Avalon Read and check against expected values
    task check_avalon_read(input [15:0] exp_count, input [1:0] exp_dir);
        reg [31:0] expected_data;
        begin
            expected_data = {14'b0, exp_dir, exp_count};
            
            @(posedge clk);
            slave_address = 8'h00; 
            slave_read    = 1'b1;
            
            @(posedge clk);
            #1; // Allow time for non-blocking assignments to settle
            
            if (slave_readdata !== expected_data) begin
                $display("[FAIL] Expected: 0x%h | Got: 0x%h", expected_data, slave_readdata);
                $error("Mismatch detected in Avalon Read!");
            end else begin
                $display("[PASS] Count: %0d | Direction: %b", exp_count, exp_dir);
            end
            
            @(posedge clk);
            slave_read = 1'b0;
            #(CLK_PERIOD * 2);
        end
    endtask

    // -----------------------------------------------------------
    // MAIN TEST SEQUENCE
    // -----------------------------------------------------------
    initial begin
        $dumpfile("dump.vcd");
        $dumpvars(0, quad_decod_demo_tb_advanced); 

        // 1. Initialize
        clk             = 1'b0;
        reset           = 1'b1;
        slave_address   = 8'h00;
        slave_read      = 1'b0;
        slave_write     = 1'b0;
        slave_writedata = 32'h0;
        slave_byteenable = 4'b1111;
        SW              = 4'b0000; 

        // 2. Release Reset
        #(CLK_PERIOD * 5);
        @(posedge clk) reset = 1'b0;
        #(CLK_PERIOD * 5);
        
        $display("============================================");
        $display(" Starting Automated Quadrature Decoder Test");
        $display("============================================");

        // 3. Test Clockwise Rotation (Right)
        $display("\n--- Testing Clockwise (Right) Rotation ---");
        rotate_encoder(4, 1); // Rotate CW by 4 states (1 full tick)
        check_avalon_read(16'd1, 2'b01); 

        rotate_encoder(8, 1); // Rotate CW by 8 states (2 full ticks)
        check_avalon_read(16'd3, 2'b01);

        // 4. Test Counter-Clockwise Rotation (Left)
        $display("\n--- Testing Counter-Clockwise (Left) Rotation ---");
        rotate_encoder(4, 0); // Rotate CCW by 4 states (1 full tick back)
        check_avalon_read(16'd2, 2'b10);

        rotate_encoder(12, 0); // Rotate CCW by 12 states (3 full ticks back)
        // Since we were at 2, going back 3 should wrap around to 16'hFFFF
        check_avalon_read(16'hFFFF, 2'b10);

        // 5. Test Reset Mid-Operation
        $display("\n--- Testing Asynchronous Reset Behavior ---");
        rotate_encoder(2, 1); // Move halfway into a state
        reset = 1'b1;
        #(CLK_PERIOD * 2);
        reset = 1'b0;
        #(CLK_PERIOD * 2);
        
        // After reset, count should be 0 and direction 0
        check_avalon_read(16'd0, 2'b00);

        $display("\n============================================");
        $display(" Simulation Complete");
        $display("============================================");
        $finish;
    end

endmodule

Assignment_7/testbench/dump.vcd
$date
	Mon May 18 13:46:17 2026
$end
$version
	Icarus Verilog
$end
$timescale
	1ps
$end
$scope module quad_decod_demo_tb_advanced $end
$var wire 8 ! user_output [7:0] $end
$var wire 32 " slave_readdata [31:0] $end
$var parameter 32 # CLK_PERIOD $end
$var parameter 32 $ DATA_WIDTH $end
$var reg 4 % SW [3:0] $end
$var reg 1 & clk $end
$var reg 1 ' reset $end
$var reg 8 ( slave_address [7:0] $end
$var reg 4 ) slave_byteenable [3:0] $end
$var reg 1 * slave_read $end
$var reg 1 + slave_write $end
$var reg 32 , slave_writedata [31:0] $end
$var integer 32 - enc_state [31:0] $end
$scope module uut $end
$var wire 4 . SW [3:0] $end
$var wire 1 & clk $end
$var wire 1 ' reset $end
$var wire 8 / slave_address [7:0] $end
$var wire 4 0 slave_byteenable [3:0] $end
$var wire 1 * slave_read $end
$var wire 1 + slave_write $end
$var wire 32 1 slave_writedata [31:0] $end
$var wire 8 2 user_output [7:0] $end
$var wire 2 3 direction [1:0] $end
$var wire 16 4 count [15:0] $end
$var parameter 32 5 DATA_WIDTH $end
$var reg 32 6 slave_readdata [31:0] $end
$scope module my_ip $end
$var wire 1 & clk $end
$var wire 2 7 direction_out [1:0] $end
$var wire 16 8 out [15:0] $end
$var wire 1 9 quadA $end
$var wire 1 : quadB $end
$var wire 1 ' reset $end
$var reg 16 ; count [15:0] $end
$var reg 2 < curr_state [1:0] $end
$var reg 2 = direction [1:0] $end
$var reg 2 > prev_state [1:0] $end
$var reg 2 ? sync [1:0] $end
$upscope $end
$upscope $end
$scope task check_avalon_read $end
$var reg 16 @ exp_count [15:0] $end
$var reg 2 A exp_dir [1:0] $end
$var reg 32 B expected_data [31:0] $end
$upscope $end
$scope task rotate_encoder $end
$var integer 32 C dir [31:0] $end
$var integer 32 D i [31:0] $end
$var integer 32 E steps [31:0] $end
$upscope $end
$upscope $end
$enddefinitions $end
$comment Show the parameter values. $end
$dumpall
b100000 5
b100000 $
b10100 #
$end
#0
$dumpvars
bx E
bx D
bx C
bx B
bx A
bx @
b0 ?
b0 >
b0 =
b0 <
b0 ;
0:
09
b0 8
b0 7
b0 6
b0 4
b0 3
b0 2
b0 1
b1111 0
b0 /
b0 .
b0 -
b0 ,
0+
0*
b1111 )
b0 (
1'
0&
b0 %
b0 "
b0 !
$end
#10000
1&
#20000
0&
#30000
1&
#40000
0&
#50000
1&
#60000
0&
#70000
1&
#80000
0&
#90000
1&
#100000
0&
#110000
0'
1&
#120000
0&
#130000
1&
#140000
0&
#150000
1&
#160000
0&
#170000
1&
#180000
0&
#190000
1&
#200000
0&
#210000
b10 ?
19
1&
b1 %
b1 .
b1 -
b0 D
b1 C
b100 E
#220000
0&
#230000
b10 <
1&
#240000
0&
#250000
b1 !
b1 2
b10 3
b10 7
b10 =
b10 >
b1 4
b1 8
b1 ;
1&
#260000
0&
#270000
1&
#280000
0&
#290000
1&
#300000
0&
#310000
b11 ?
1:
1&
b11 %
b11 .
b10 -
b1 D
#320000
0&
#330000
b11 <
1&
#340000
0&
#350000
b10 !
b10 2
b11 >
b10 4
b10 8
b10 ;
1&
#360000
0&
#370000
1&
#380000
0&
#390000
1&
#400000
0&
#410000
b1 ?
09
1&
b10 %
b10 .
b11 -
b10 D
#420000
0&
#430000
b1 <
1&
#440000
0&
#450000
b11 !
b11 2
b1 3
b1 7
b1 =
b1 >
b11 4
b11 8
b11 ;
1&
#460000
0&
#470000
1&
#480000
0&
#490000
1&
#500000
0&
#510000
b0 ?
0:
1&
b0 %
b0 .
b0 -
b11 D
#520000
0&
#530000
b0 <
1&
#540000
0&
#550000
b100 !
b100 2
b0 >
b100 4
b100 8
b100 ;
1&
#560000
0&
#570000
1&
#580000
0&
#590000
1&
#600000
0&
#610000
b10000000000000100 "
b10000000000000100 6
1*
1&
b10000000000000001 B
b1 A
b1 @
b100 D
#620000
0&
#630000
1&
#640000
0&
#650000
0*
1&
#660000
0&
#670000
1&
#680000
0&
#690000
b10 ?
19
1&
b1 %
b1 .
b1 -
b0 D
b1000 E
#700000
0&
#710000
b10 <
1&
#720000
0&
#730000
b101 !
b101 2
b10 3
b10 7
b10 =
b10 >
b101 4
b101 8
b101 ;
1&
#740000
0&
#750000
1&
#760000
0&
#770000
1&
#780000
0&
#790000
b11 ?
1:
1&
b11 %
b11 .
b10 -
b1 D
#800000
0&
#810000
b11 <
1&
#820000
0&
#830000
b110 !
b110 2
b11 >
b110 4
b110 8
b110 ;
1&
#840000
0&
#850000
1&
#860000
0&
#870000
1&
#880000
0&
#890000
b1 ?
09
1&
b10 %
b10 .
b11 -
b10 D
#900000
0&
#910000
b1 <
1&
#920000
0&
#930000
b111 !
b111 2
b1 3
b1 7
b1 =
b1 >
b111 4
b111 8
b111 ;
1&
#940000
0&
#950000
1&
#960000
0&
#970000
1&
#980000
0&
#990000
b0 ?
0:
1&
b0 %
b0 .
b0 -
b11 D
#1000000
0&
#1010000
b0 <
1&
#1020000
0&
#1030000
b1000 !
b1000 2
b0 >
b1000 4
b1000 8
b1000 ;
1&
#1040000
0&
#1050000
1&
#1060000
0&
#1070000
1&
#1080000
0&
#1090000
b10 ?
19
1&
b1 %
b1 .
b1 -
b100 D
#1100000
0&
#1110000
b10 <
1&
#1120000
0&
#1130000
b1001 !
b1001 2
b10 3
b10 7
b10 =
b10 >
b1001 4
b1001 8
b1001 ;
1&
#1140000
0&
#1150000
1&
#1160000
0&
#1170000
1&
#1180000
0&
#1190000
b11 ?
1:
1&
b11 %
b11 .
b10 -
b101 D
#1200000
0&
#1210000
b11 <
1&
#1220000
0&
#1230000
b1010 !
b1010 2
b11 >
b1010 4
b1010 8
b1010 ;
1&
#1240000
0&
#1250000
1&
#1260000
0&
#1270000
1&
#1280000
0&
#1290000
b1 ?
09
1&
b10 %
b10 .
b11 -
b110 D
#1300000
0&
#1310000
b1 <
1&
#1320000
0&
#1330000
b1011 !
b1011 2
b1 3
b1 7
b1 =
b1 >
b1011 4
b1011 8
b1011 ;
1&
#1340000
0&
#1350000
1&
#1360000
0&
#1370000
1&
#1380000
0&
#1390000
b0 ?
0:
1&
b0 %
b0 .
b0 -
b111 D
#1400000
0&
#1410000
b0 <
1&
#1420000
0&
#1430000
b1100 !
b1100 2
b0 >
b1100 4
b1100 8
b1100 ;
1&
#1440000
0&
#1450000
1&
#1460000
0&
#1470000
1&
#1480000
0&
#1490000
b10000000000001100 "
b10000000000001100 6
1*
1&
b10000000000000011 B
b11 @
b1000 D
#1500000
0&
#1510000
1&
#1520000
0&
#1530000
0*
1&
#1540000
0&
#1550000
1&
#1560000
0&
#1570000
b1 ?
1:
1&
b10 %
b10 .
b11 -
b0 D
b0 C
b100 E
#1580000
0&
#1590000
b1 <
1&
#1600000
0&
#1610000
b1011 !
b1011 2
b10 3
b10 7
b10 =
b1 >
b1011 4
b1011 8
b1011 ;
1&
#1620000
0&
#1630000
1&
#1640000
0&
#1650000
1&
#1660000
0&
#1670000
b11 ?
19
1&
b11 %
b11 .
b10 -
b1 D
#1680000
0&
#1690000
b11 <
1&
#1700000
0&
#1710000
b1010 !
b1010 2
b1 3
b1 7
b1 =
b11 >
b1010 4
b1010 8
b1010 ;
1&
#1720000
0&
#1730000
1&
#1740000
0&
#1750000
1&
#1760000
0&
#1770000
b10 ?
0:
1&
b1 %
b1 .
b1 -
b10 D
#1780000
0&
#1790000
b10 <
1&
#1800000
0&
#1810000
b1001 !
b1001 2
b10 >
b1001 4
b1001 8
b1001 ;
1&
#1820000
0&
#1830000
1&
#1840000
0&
#1850000
1&
#1860000
0&
#1870000
b0 ?
09
1&
b0 %
b0 .
b0 -
b11 D
#1880000
0&
#1890000
b0 <
1&
#1900000
0&
#1910000
b1000 !
b1000 2
b10 3
b10 7
b10 =
b0 >
b1000 4
b1000 8
b1000 ;
1&
#1920000
0&
#1930000
1&
#1940000
0&
#1950000
1&
#1960000
0&
#1970000
b100000000000001000 "
b100000000000001000 6
1*
1&
b100000000000000010 B
b10 A
b10 @
b100 D
#1980000
0&
#1990000
1&
#2000000
0&
#2010000
0*
1&
#2020000
0&
#2030000
1&
#2040000
0&
#2050000
b1 ?
1:
1&
b10 %
b10 .
b11 -
b0 D
b1100 E
#2060000
0&
#2070000
b1 <
1&
#2080000
0&
#2090000
b111 !
b111 2
b1 >
b111 4
b111 8
b111 ;
1&
#2100000
0&
#2110000
1&
#2120000
0&
#2130000
1&
#2140000
0&
#2150000
b11 ?
19
1&
b11 %
b11 .
b10 -
b1 D
#2160000
0&
#2170000
b11 <
1&
#2180000
0&
#2190000
b110 !
b110 2
b1 3
b1 7
b1 =
b11 >
b110 4
b110 8
b110 ;
1&
#2200000
0&
#2210000
1&
#2220000
0&
#2230000
1&
#2240000
0&
#2250000
b10 ?
0:
1&
b1 %
b1 .
b1 -
b10 D
#2260000
0&
#2270000
b10 <
1&
#2280000
0&
#2290000
b101 !
b101 2
b10 >
b101 4
b101 8
b101 ;
1&
#2300000
0&
#2310000
1&
#2320000
0&
#2330000
1&
#2340000
0&
#2350000
b0 ?
09
1&
b0 %
b0 .
b0 -
b11 D
#2360000
0&
#2370000
b0 <
1&
#2380000
0&
#2390000
b100 !
b100 2
b10 3
b10 7
b10 =
b0 >
b100 4
b100 8
b100 ;
1&
#2400000
0&
#2410000
1&
#2420000
0&
#2430000
1&
#2440000
0&
#2450000
b1 ?
1:
1&
b10 %
b10 .
b11 -
b100 D
#2460000
0&
#2470000
b1 <
1&
#2480000
0&
#2490000
b11 !
b11 2
b1 >
b11 4
b11 8
b11 ;
1&
#2500000
0&
#2510000
1&
#2520000
0&
#2530000
1&
#2540000
0&
#2550000
b11 ?
19
1&
b11 %
b11 .
b10 -
b101 D
#2560000
0&
#2570000
b11 <
1&
#2580000
0&
#2590000
b10 !
b10 2
b1 3
b1 7
b1 =
b11 >
b10 4
b10 8
b10 ;
1&
#2600000
0&
#2610000
1&
#2620000
0&
#2630000
1&
#2640000
0&
#2650000
b10 ?
0:
1&
b1 %
b1 .
b1 -
b110 D
#2660000
0&
#2670000
b10 <
1&
#2680000
0&
#2690000
b1 !
b1 2
b10 >
b1 4
b1 8
b1 ;
1&
#2700000
0&
#2710000
1&
#2720000
0&
#2730000
1&
#2740000
0&
#2750000
b0 ?
09
1&
b0 %
b0 .
b0 -
b111 D
#2760000
0&
#2770000
b0 <
1&
#2780000
0&
#2790000
b0 !
b0 2
b10 3
b10 7
b10 =
b0 >
b0 4
b0 8
b0 ;
1&
#2800000
0&
#2810000
1&
#2820000
0&
#2830000
1&
#2840000
0&
#2850000
b1 ?
1:
1&
b10 %
b10 .
b11 -
b1000 D
#2860000
0&
#2870000
b1 <
1&
#2880000
0&
#2890000
b11111111 !
b11111111 2
b1 >
b1111111111111111 4
b1111111111111111 8
b1111111111111111 ;
1&
#2900000
0&
#2910000
1&
#2920000
0&
#2930000
1&
#2940000
0&
#2950000
b11 ?
19
1&
b11 %
b11 .
b10 -
b1001 D
#2960000
0&
#2970000
b11 <
1&
#2980000
0&
#2990000
b11111110 !
b11111110 2
b1 3
b1 7
b1 =
b11 >
b1111111111111110 4
b1111111111111110 8
b1111111111111110 ;
1&
#3000000
0&
#3010000
1&
#3020000
0&
#3030000
1&
#3040000
0&
#3050000
b10 ?
0:
1&
b1 %
b1 .
b1 -
b1010 D
#3060000
0&
#3070000
b10 <
1&
#3080000
0&
#3090000
b11111101 !
b11111101 2
b10 >
b1111111111111101 4
b1111111111111101 8
b1111111111111101 ;
1&
#3100000
0&
#3110000
1&
#3120000
0&
#3130000
1&
#3140000
0&
#3150000
b0 ?
09
1&
b0 %
b0 .
b0 -
b1011 D
#3160000
0&
#3170000
b0 <
1&
#3180000
0&
#3190000
b11111100 !
b11111100 2
b10 3
b10 7
b10 =
b0 >
b1111111111111100 4
b1111111111111100 8
b1111111111111100 ;
1&
#3200000
0&
#3210000
1&
#3220000
0&
#3230000
1&
#3240000
0&
#3250000
b101111111111111100 "
b101111111111111100 6
1*
1&
b101111111111111111 B
b1111111111111111 @
b1100 D
#3260000
0&
#3270000
1&
#3280000
0&
#3290000
0*
1&
#3300000
0&
#3310000
1&
#3320000
0&
#3330000
b10 ?
19
1&
b1 %
b1 .
b1 -
b0 D
b1 C
b10 E
#3340000
0&
#3350000
b10 <
1&
#3360000
0&
#3370000
b11111101 !
b11111101 2
b10 >
b1111111111111101 4
b1111111111111101 8
b1111111111111101 ;
1&
#3380000
0&
#3390000
1&
#3400000
0&
#3410000
1&
#3420000
0&
#3430000
b11 ?
1:
1&
b11 %
b11 .
b10 -
b1 D
#3440000
0&
#3450000
b11 <
1&
#3460000
0&
#3470000
b11111110 !
b11111110 2
b11 >
b1111111111111110 4
b1111111111111110 8
b1111111111111110 ;
1&
#3480000
0&
#3490000
1&
#3500000
0&
#3510000
1&
#3520000
0&
#3530000
b0 !
b0 2
b0 "
b0 6
b0 >
b0 3
b0 7
b0 =
b0 4
b0 8
b0 ;
1&
1'
b10 D
#3540000
0&
#3550000
1&
#3560000
0&
#3570000
1&
0'
#3580000
0&
#3590000
1&
#3600000
0&
#3610000
1*
1&
b0 B
b0 A
b0 @
#3620000
0&
#3630000
1&
#3640000
0&
#3650000
0*
1&
