Assignment_4/quad_decod.v
//
// Authors: D. Gaethofs, D.A. Rooijackers
// Title: Assignment 4 
// Brief: Quadrature Decoder 
//

module quad_decod(
    input quadA, 
    input quadB, 
    input clk, 
    output reg [15:0] count = 0, 
    output reg [1:0] direction = 0
);

    reg [1:0] curr_state;
    reg [1:0] prev_state = 2'b00;

always @ (posedge clk)
begin
    
    curr_state <= {quadA, quadB};

    case (curr_state)
        2'b00:
            begin
                if (prev_state == 2'b01)
                    begin
                        count <= count + 1;
                        prev_state <= curr_state;
                        direction = 2'b01; //right
                    end 
                else if (prev_state == 2'b10)
                    begin
                       count <= count - 1;
                       prev_state <= curr_state;
                       direction = 2'b10; //left 
                    end
            end
        2'b01:
            begin
                if (prev_state == 2'b00)
                    begin
                        count <= count - 1;
                        prev_state <= curr_state;
                        direction = 2'b10; //left
                    end 
                else if (prev_state == 2'b11)
                    begin
                       count <= count + 1;
                       prev_state <= curr_state;
                       direction = 2'b01; //right 
                    end
            end
        2'b10:
            begin
                if (prev_state == 2'b00)
                    begin
                        count <= count + 1;
                        prev_state <= curr_state;
                        direction = 2'b10; //right
                    end 
                else if (prev_state == 2'b11)
                    begin
                       count <= count - 1;
                       prev_state <= curr_state;
                       direction = 2'b01; //left 
                    end
            end
        2'b11:
            begin
                if (prev_state == 2'b10)
                    begin
                        count <= count + 1;
                        prev_state <= curr_state;
                        direction = 2'b10; //right
                    end 
                else if (prev_state == 2'b01)
                    begin
                       count <= count - 1;
                       prev_state <= curr_state;
                       direction = 2'b01; //left 
                    end
            end
    endcase

end

endmodule

Assignment_4/tb_quad_decod.v

`include "quad_decod.v"
`timescale 1ns/1ps

module tb_quad_decod;

    reg quadA;
    reg quadB;
    reg clk;
    wire [15:0] count;
    wire [1:0] direction;
    integer i;
    integer j;


    quad_decod #() dut (
        .quadA(quadA),
        .quadB(quadB),
        .clk(clk),
        .count(count),
        .direction(direction)
    );

    initial 
    begin
        clk = 0;
        forever #10 clk = ~clk;
    end

    initial
    begin
        quadA = 1;
        for (i = 0; i < 10; i = i + 1) begin
            #100;
            quadA = ~quadA;
        end

        quadA = 0;
        #100;
        quadA = 1;
        for (i = 0; i < 10; i = i + 1) begin
            #100;
            quadA = ~quadA;
        end
    end

    initial 
    begin
        quadB = 0;
        #50;
        quadB = 1;
        for (j = 0; j < 10; j = j + 1) begin
            #100;
            quadB = ~quadB;
        end

        quadB = 1;
        for (j = 0; j < 10; j = j + 1) begin
            #100;
            quadB = ~quadB;
        end
    end

    initial begin
        $dumpfile("signals.vcd");
        $dumpvars(0, tb_quad_decod);
        #10000;
        $finish;
    end

endmodule

Assignment_4/signals.vcd
$date
	Thu Apr 30 10:01:41 2026
$end
$version
	Icarus Verilog
$end
$timescale
	1ps
$end
$scope module tb_quad_decod $end
$var wire 2 ! direction [1:0] $end
$var wire 16 " count [15:0] $end
$var reg 1 # clk $end
$var reg 1 $ quadA $end
$var reg 1 % quadB $end
$var integer 32 & i [31:0] $end
$var integer 32 ' j [31:0] $end
$scope module dut $end
$var wire 1 # clk $end
$var wire 1 $ quadA $end
$var wire 1 % quadB $end
$var reg 16 ( count [15:0] $end
$var reg 2 ) curr_state [1:0] $end
$var reg 2 * direction [1:0] $end
$var reg 2 + prev_state [1:0] $end
$upscope $end
$upscope $end
$enddefinitions $end
$comment Show the parameter values. $end
$dumpall
$end
#0
$dumpvars
b0 +
b0 *
bx )
b0 (
bx '
b0 &
0%
1$
0#
b0 "
b0 !
$end
#10000
b10 )
1#
#20000
0#
#30000
b10 +
b1 "
b1 (
b10 !
b10 *
1#
#40000
0#
#50000
b11 )
1#
b0 '
1%
#60000
0#
#70000
b11 +
b10 "
b10 (
1#
#80000
0#
#90000
1#
#100000
0#
b1 &
0$
#110000
b1 )
1#
#120000
0#
#130000
b1 +
b11 "
b11 (
b1 !
b1 *
1#
#140000
0#
#150000
b0 )
1#
b1 '
0%
#160000
0#
#170000
b0 +
b100 "
b100 (
1#
#180000
0#
#190000
1#
#200000
0#
b10 &
1$
#210000
b10 )
1#
#220000
0#
#230000
b10 +
b101 "
b101 (
b10 !
b10 *
1#
#240000
0#
#250000
b11 )
1#
b10 '
1%
#260000
0#
#270000
b11 +
b110 "
b110 (
1#
#280000
0#
#290000
1#
#300000
0#
b11 &
0$
#310000
b1 )
1#
#320000
0#
#330000
b1 +
b111 "
b111 (
b1 !
b1 *
1#
#340000
0#
#350000
b0 )
1#
b11 '
0%
#360000
0#
#370000
b0 +
b1000 "
b1000 (
1#
#380000
0#
#390000
1#
#400000
0#
b100 &
1$
#410000
b10 )
1#
#420000
0#
#430000
b10 +
b1001 "
b1001 (
b10 !
b10 *
1#
#440000
0#
#450000
b11 )
1#
b100 '
1%
#460000
0#
#470000
b11 +
b1010 "
b1010 (
1#
#480000
0#
#490000
1#
#500000
0#
b101 &
0$
#510000
b1 )
1#
#520000
0#
#530000
b1 +
b1011 "
b1011 (
b1 !
b1 *
1#
#540000
0#
#550000
b0 )
1#
b101 '
0%
#560000
0#
#570000
b0 +
b1100 "
b1100 (
1#
#580000
0#
#590000
1#
#600000
0#
b110 &
1$
#610000
b10 )
1#
#620000
0#
#630000
b10 +
b1101 "
b1101 (
b10 !
b10 *
1#
#640000
0#
#650000
b11 )
1#
b110 '
1%
#660000
0#
#670000
b11 +
b1110 "
b1110 (
1#
#680000
0#
#690000
1#
#700000
0#
b111 &
0$
#710000
b1 )
1#
#720000
0#
#730000
b1 +
b1111 "
b1111 (
b1 !
b1 *
1#
#740000
0#
#750000
b0 )
1#
b111 '
0%
#760000
0#
#770000
b0 +
b10000 "
b10000 (
1#
#780000
0#
#790000
1#
#800000
0#
b1000 &
1$
#810000
b10 )
1#
#820000
0#
#830000
b10 +
b10001 "
b10001 (
b10 !
b10 *
1#
#840000
0#
#850000
b11 )
1#
b1000 '
1%
#860000
0#
#870000
b11 +
b10010 "
b10010 (
1#
#880000
0#
#890000
1#
#900000
0#
b1001 &
0$
#910000
b1 )
1#
#920000
0#
#930000
b1 +
b10011 "
b10011 (
b1 !
b1 *
1#
#940000
0#
#950000
b0 )
1#
b1001 '
0%
#960000
0#
#970000
b0 +
b10100 "
b10100 (
1#
#980000
0#
#990000
1#
#1000000
0#
b1010 &
0$
#1010000
1#
#1020000
0#
#1030000
1#
#1040000
0#
#1050000
b1 )
1#
b0 '
1%
#1060000
0#
#1070000
b1 +
b10011 "
b10011 (
b10 !
b10 *
1#
#1080000
0#
#1090000
1#
#1100000
0#
b0 &
1$
#1110000
b11 )
1#
#1120000
0#
#1130000
b11 +
b10010 "
b10010 (
b1 !
b1 *
1#
#1140000
0#
#1150000
b10 )
1#
b1 '
0%
#1160000
0#
#1170000
b10 +
b10001 "
b10001 (
1#
#1180000
0#
#1190000
1#
#1200000
0#
b1 &
0$
#1210000
b0 )
1#
#1220000
0#
#1230000
b0 +
b10000 "
b10000 (
b10 !
b10 *
1#
#1240000
0#
#1250000
b1 )
1#
b10 '
1%
#1260000
0#
#1270000
b1 +
b1111 "
b1111 (
1#
#1280000
0#
#1290000
1#
#1300000
0#
b10 &
1$
#1310000
b11 )
1#
#1320000
0#
#1330000
b11 +
b1110 "
b1110 (
b1 !
b1 *
1#
#1340000
0#
#1350000
b10 )
1#
b11 '
0%
#1360000
0#
#1370000
b10 +
b1101 "
b1101 (
1#
#1380000
0#
#1390000
1#
#1400000
0#
b11 &
0$
#1410000
b0 )
1#
#1420000
0#
#1430000
b0 +
b1100 "
b1100 (
b10 !
b10 *
1#
#1440000
0#
#1450000
b1 )
1#
b100 '
1%
#1460000
0#
#1470000
b1 +
b1011 "
b1011 (
1#
#1480000
0#
#1490000
1#
#1500000
0#
b100 &
1$
#1510000
b11 )
1#
#1520000
0#
#1530000
b11 +
b1010 "
b1010 (
b1 !
b1 *
1#
#1540000
0#
#1550000
b10 )
1#
b101 '
0%
#1560000
0#
#1570000
b10 +
b1001 "
b1001 (
1#
#1580000
0#
#1590000
1#
#1600000
0#
b101 &
0$
#1610000
b0 )
1#
#1620000
0#
#1630000
b0 +
b1000 "
b1000 (
b10 !
b10 *
1#
#1640000
0#
#1650000
b1 )
1#
b110 '
1%
#1660000
0#
#1670000
b1 +
b111 "
b111 (
1#
#1680000
0#
#1690000
1#
#1700000
0#
b110 &
1$
#1710000
b11 )
1#
#1720000
0#
#1730000
b11 +
b110 "
b110 (
b1 !
b1 *
1#
#1740000
0#
#1750000
b10 )
1#
b111 '
0%
#1760000
0#
#1770000
b10 +
b101 "
b101 (
1#
#1780000
0#
#1790000
1#
#1800000
0#
b111 &
0$
#1810000
b0 )
1#
#1820000
0#
#1830000
b0 +
b100 "
b100 (
b10 !
b10 *
1#
#1840000
0#
#1850000
b1 )
1#
b1000 '
1%
#1860000
0#
#1870000
b1 +
b11 "
b11 (
1#
#1880000
0#
#1890000
1#
#1900000
0#
b1000 &
1$
#1910000
b11 )
1#
#1920000
0#
#1930000
b11 +
b10 "
b10 (
b1 !
b1 *
1#
#1940000
0#
#1950000
b10 )
1#
b1001 '
0%
#1960000
0#
#1970000
b10 +
b1 "
b1 (
1#
#1980000
0#
#1990000
1#
#2000000
0#
b1001 &
0$
#2010000
b0 )
1#
#2020000
0#
#2030000
b0 +
b0 "
b0 (
b10 !
b10 *
1#
#2040000
0#
#2050000
b1 )
1#
b1010 '
1%
#2060000
0#
#2070000
b1 +
b1111111111111111 "
b1111111111111111 (
1#
#2080000
0#
#2090000
1#
#2100000
0#
b1010 &
1$
#2110000
b11 )
1#
#2120000
0#
#2130000
b11 +
b1111111111111110 "
b1111111111111110 (
b1 !
b1 *
1#
